CHANGELOG.md
LICENSE
README.md
SECURITY.md
mlpr/__init__.py
mlpr/ml/__init__.py
mlpr/ml/supervisioned/__init__.py
mlpr/ml/supervisioned/classification/__init__.py
mlpr/ml/supervisioned/classification/metrics.py
mlpr/ml/supervisioned/classification/uncertainty.py
mlpr/ml/supervisioned/classification/utils.py
mlpr/ml/supervisioned/forecasting/__init__.py
mlpr/ml/supervisioned/regression/__init__.py
mlpr/ml/supervisioned/regression/metrics.py
mlpr/ml/supervisioned/regression/plots.py
mlpr/ml/supervisioned/surrogates/__init__.py
mlpr/ml/supervisioned/surrogates/surrogates.py
mlpr/ml/supervisioned/tunning/__init__.py
mlpr/ml/supervisioned/tunning/grid_search.py
mlpr/reports/__init__.py
mlpr/reports/create.py
mlpr-0.1.19.dist-info/LICENSE
mlpr-0.1.19.dist-info/METADATA
mlpr-0.1.19.dist-info/WHEEL
mlpr-0.1.19.dist-info/RECORD
