Metadata-Version: 2.1
Name: mlpr
Version: 0.1.19
Summary: A library for machine learning pipeline and creation of reports.
Author: Manuel Ferreira Junior
Author-email: ferreira.jr.ufpb@gmail.com
Maintainer: Manuel Ferreira Junior
Maintainer-email: ferreira.jr.ufpb@gmail.com
Requires-Python: >=3.9
Classifier: Development Status :: 3 - Alpha
Classifier: Intended Audience :: Developers
Classifier: Intended Audience :: Science/Research
Classifier: License :: OSI Approved :: MIT License
Classifier: Operating System :: MacOS
Classifier: Operating System :: Microsoft :: Windows
Classifier: Operating System :: Unix
Classifier: Programming Language :: Python
Classifier: Programming Language :: Python :: 3
Classifier: Programming Language :: Python :: 3.9
Classifier: Programming Language :: Python :: 3.10
Classifier: Programming Language :: Python :: 3.11
Classifier: Programming Language :: Python :: 3.12
Classifier: Topic :: Scientific/Engineering :: Artificial Intelligence
Classifier: Topic :: Scientific/Engineering :: Mathematics
Classifier: Topic :: Scientific/Engineering :: Visualization
Classifier: Topic :: Software Development
Requires-Dist: Jinja2 (>=3.1.3,<4.0.0)
Requires-Dist: matplotlib (>=3.8.4,<4.0.0)
Requires-Dist: numpy (>=1.25.0,<2.0.0)
Requires-Dist: pandas (>=2.2.2,<3.0.0)
Requires-Dist: pyspark (>=3.5.1,<4.0.0)
Requires-Dist: scikit-learn (>=1.4.2,<2.0.0)
Requires-Dist: scipy (>=1.11.0,<2.0.0)
Requires-Dist: statsmodels (>=0.14.2,<0.15.0)
Requires-Dist: tqdm (>=4.66.4,<5.0.0)
Project-URL: changelog, https://github.com/Manuelfjr/mlpr/tree/develop/CHANGELOG.md
Project-URL: homepage, https://github.com/Manuelfjr/mlpr/tree/develop
Project-URL: issues, https://github.com/Manuelfjr/mlpr/issues
Project-URL: repository, https://github.com/Manuelfjr/mlpr.git
Project-URL: source, https://github.com/Manuelfjr/mlpr
Project-URL: tracker, https://github.com/Manuelfjr/mlpr/tree/develop/issues
